python_web_io/__init__.py
python_web_io/cache.py
python_web_io/main.py
python_web_io/override.py
python_web_io/templates/base.html
python_web_io/templates/error.html
python_web_io/templates/index.html
python_web_io-0.2.3.dist-info/METADATA
python_web_io-0.2.3.dist-info/WHEEL
python_web_io-0.2.3.dist-info/entry_points.txt
python_web_io-0.2.3.dist-info/RECORD
