Metadata-Version: 2.1
Name: python-web-io
Version: 0.2.3
Summary: Generate a webpage as a GUI for a Python script, and serve from anywhere.
Home-page: https://github.com/Cutwell/python-web-io
License: MIT
Author: Zachary Smith
Author-email: zachsmith.dev@gmail.com
Requires-Python: >=3.10,<4.0
Classifier: License :: OSI Approved :: MIT License
Classifier: Programming Language :: Python :: 3
Classifier: Programming Language :: Python :: 3.10
Classifier: Programming Language :: Python :: 3.11
Requires-Dist: fastapi[all] (>=0.101.0,<0.102.0)
Requires-Dist: jinja2 (>=3.1.2,<4.0.0)
Requires-Dist: markdown (>=3.4.3,<4.0.0)
Requires-Dist: pydantic (>=2.1.1,<3.0.0)
Requires-Dist: python-multipart (>=0.0.6,<0.0.7)
Requires-Dist: starsessions (>=2.1.2,<3.0.0)
Requires-Dist: toml (>=0.10.2,<0.11.0)
Requires-Dist: uvicorn (>=0.23.2,<0.24.0)
Requires-Dist: watchdog (>=3.0.0,<4.0.0)
Project-URL: Repository, https://github.com/Cutwell/python-web-io
